MANIFEST.in
README.rst
setup.py
docs/__init__.py
docs/source/__init__.py
docs/source/conf.py
limis/__init__.py
limis.egg-info/PKG-INFO
limis.egg-info/SOURCES.txt
limis.egg-info/dependency_links.txt
limis.egg-info/entry_points.txt
limis.egg-info/not-zip-safe
limis.egg-info/requires.txt
limis.egg-info/top_level.txt
limis/bin/limis-management.py
limis/core/__init__.py
limis/core/environment.py
limis/core/logging.conf
limis/core/messages.py
limis/core/settings.ini
limis/core/utilities.py
limis/management/__init__.py
limis/management/commands.py
limis/management/exit_codes.py
limis/management/messages.py
limis/resources/__init__.py
limis/resources/__pycache__/__init__.cpython-37.pyc
limis/resources/project_template/management.py.tpl
limis/resources/project_template/project/__init__.py.tpl
limis/resources/project_template/project/services.py.tpl
limis/resources/project_template/project/settings.ini.tpl
limis/resources/service_template/__init__.py.tpl
limis/resources/service_template/components.py.tpl
limis/resources/service_template/handlers.py.tpl
limis/resources/service_template/services.py.tpl
limis/server/__init__.py
limis/server/messages.py
limis/server/settings.ini
limis/services/__init__.py
limis/services/components.py
limis/services/handlers.py
limis/services/messages.py
limis/services/router.py
limis/test/__init__.py
tests/__init__.py
tests/core/__init__.py
tests/core/test_init.py
tests/core/test_utilities.py
tests/management/__init__.py
tests/management/test_commands.py
tests/management/test_init.py
tests/server/__init__.py
tests/server/test_init.py
tests/services/__init__.py
tests/services/test_components.py
tests/services/test_handlers.py
tests/services/test_init.py
tests/services/test_router.py